ara_api_lua/__init__.py
ara_api_lua/__main__.py
ara_api_lua/_core/__init__.py
ara_api_lua/_core/adapters/__init__.py
ara_api_lua/_core/adapters/ara_link_lua.py
ara_api_lua/_core/bridge/__init__.py
ara_api_lua/_core/bridge/lua_bridge.py
ara_api_lua/_utils/__init__.py
ara_api_lua/_utils/config.py
ara_api_lua/_utils/decorators.py
ara_api_lua/_utils/logger.py
ara_api_lua/_utils/communication/__init__.py
ara_api_lua/_utils/communication/grpc_sync.py
ara_api_lua/_utils/communication/grpc/msp_pb2.py
ara_api_lua/_utils/communication/grpc/msp_pb2_grpc.py
ara_api_lua/_utils/communication/grpc/navigation_pb2.py
ara_api_lua/_utils/communication/grpc/navigation_pb2_grpc.py
ara_api_lua/_utils/communication/grpc/vision_pb2.py
ara_api_lua/_utils/communication/grpc/vision_pb2_grpc.py
ara_api_lua/_utils/communication/grpc/messages/base_msg_pb2.py
ara_api_lua/_utils/communication/grpc/messages/base_msg_pb2_grpc.py
ara_api_lua/_utils/communication/grpc/messages/msp_msg_pb2.py
ara_api_lua/_utils/communication/grpc/messages/msp_msg_pb2_grpc.py
ara_api_lua/_utils/communication/grpc/messages/nav_msg_pb2.py
ara_api_lua/_utils/communication/grpc/messages/nav_msg_pb2_grpc.py
ara_api_lua/_utils/communication/grpc/messages/vision_msg_pb2.py
ara_api_lua/_utils/communication/grpc/messages/vision_msg_pb2_grpc.py
ara_api_lua/_utils/communication/protobuf/api.proto
ara_api_lua/_utils/communication/protobuf/msp.proto
ara_api_lua/_utils/communication/protobuf/navigation.proto
ara_api_lua/_utils/communication/protobuf/vision.proto
ara_api_lua/_utils/communication/protobuf/messages/base_msg.proto
ara_api_lua/_utils/communication/protobuf/messages/msp_msg.proto
ara_api_lua/_utils/communication/protobuf/messages/nav_msg.proto
ara_api_lua/_utils/communication/protobuf/messages/vision_msg.proto
ara_api_lua/_utils/examples/aruco.lua
ara_api_lua/_utils/examples/square.lua
ara_api_lua/_utils/examples/takeoff_and_land.lua
ara_api_lua-1.1.0.dist-info/METADATA
ara_api_lua-1.1.0.dist-info/WHEEL
ara_api_lua-1.1.0.dist-info/entry_points.txt
ara_api_lua-1.1.0.dist-info/licenses/LICENSE
ara_api_lua-1.1.0.dist-info/RECORD
