Metadata-Version: 2.4
Name: ara-api-lua
Version: 1.1.0
Summary: Add your description here
Maintainer-email: Alexander Kleimenov <nequamy@gmail.com>
License: MIT
License-File: LICENSE
Keywords: API,ARA,drones,robotics
Classifier: Development Status :: 4 - Beta
Classifier: Intended Audience :: Developers
Classifier: License :: OSI Approved :: MIT License
Classifier: Operating System :: MacOS
Classifier: Operating System :: Microsoft :: Windows
Classifier: Operating System :: Unix
Classifier: Programming Language :: Python
Classifier: Programming Language :: Python :: 3
Classifier: Programming Language :: Python :: 3.8
Classifier: Programming Language :: Python :: 3.9
Classifier: Programming Language :: Python :: 3.10
Classifier: Programming Language :: Python :: 3.11
Classifier: Programming Language :: Python :: 3.12
Classifier: Programming Language :: Python :: 3.13
Classifier: Topic :: Scientific/Engineering
Classifier: Topic :: Software Development
Requires-Python: >=3.8
Requires-Dist: click>=8.1.8
Requires-Dist: grpcio-tools==1.66.2
Requires-Dist: grpcio==1.69.0
Requires-Dist: lupa>=2.6
Requires-Dist: rich>=14.2.0
